setup.py
src/acelerai_inputstream/__init__.py
src/acelerai_inputstream/cache_manager.py
src/acelerai_inputstream/http_aceler.py
src/acelerai_inputstream/inputstream_client.py
src/acelerai_inputstream/utils.py
src/acelerai_inputstream/models/__init__.py
src/acelerai_inputstream/models/asset.py
src/acelerai_inputstream/models/inputstream.py
src/acelerai_inputstream/models/pagination_data.py
src/acelerai_pipelines/__init__.py
src/acelerai_pipelines/http_aceler_pipelines.py
src/acelerai_pipelines/pipelines_client.py
src/acelerai_pipelines/util.py
src/acelerai_pipelines/models/__init__.py
src/acelerai_pipelines/models/deploy.py
src/acelerai_pipelines/models/environment_item.py
src/acelerai_pipelines/models/pagination_data.py
src/acelerai_pipelines/models/project.py
src/acelerai_pipelines/models/run.py
src/acelerai_pipelines/models/run_trigger_type.py
src/acelerai_staging.egg-info/PKG-INFO
src/acelerai_staging.egg-info/SOURCES.txt
src/acelerai_staging.egg-info/dependency_links.txt
src/acelerai_staging.egg-info/requires.txt
src/acelerai_staging.egg-info/top_level.txt
test/test.py
test/test_app.py
test/test_f.py