Metadata-Version: 2.4
Name: acelerai-staging
Version: 0.0.8
Summary: short package description
Author: DaniloAraneda
Author-email: danilo@alert2gain.com
Classifier: Programming Language :: Python :: 3
Classifier: License :: OSI Approved :: MIT License
Classifier: Operating System :: OS Independent
Requires-Python: >=3.10.0
Requires-Dist: anyio==4.8.0
Requires-Dist: certifi>=2024.7.4
Requires-Dist: charset-normalizer>=3.3.2
Requires-Dist: exceptiongroup>=1.2.2
Requires-Dist: fastjsonschema>=2.20.0
Requires-Dist: h11>=0.14.0
Requires-Dist: h2==4.1.0
Requires-Dist: hpack==4.0.0
Requires-Dist: httpcore==1.0.7
Requires-Dist: httpx==0.28.1
Requires-Dist: hyperframe==6.0.1
Requires-Dist: idna>=3.7
Requires-Dist: msgpack==1.1.0
Requires-Dist: python-dateutil>=2.9.0.post0
Requires-Dist: requests>=2.32.3
Requires-Dist: six>=1.16.0
Requires-Dist: sniffio==1.3.1
Requires-Dist: typing_extensions>=4.12.2
Requires-Dist: urllib3>=2.2.2
Dynamic: author
Dynamic: author-email
Dynamic: classifier
Dynamic: requires-dist
Dynamic: requires-python
Dynamic: summary
